sellix-py-api-wrapper/__init__.py
sellix-py-api-wrapper/sellix_api.py
sellix_py_api_wrapper/__init__.py
sellix_py_api_wrapper/sellix_api.py
sellix_py_api_wrapper-1.1.4.dist-info/METADATA
sellix_py_api_wrapper-1.1.4.dist-info/WHEEL
sellix_py_api_wrapper-1.1.4.dist-info/top_level.txt
sellix_py_api_wrapper-1.1.4.dist-info/RECORD
