Metadata-Version: 2.1
Name: sellix-py-api-wrapper
Version: 1.1.4
Summary: Sellix.IO API wrapper written in Python.
Home-page: UNKNOWN
Author: Mlchael
Author-email: 
License: UNKNOWN
Keywords: python3,sellix,sellix.io,api,api wrapper
Platform: UNKNOWN
Classifier: Programming Language :: Python :: 3
Classifier: Operating System :: Unix
Classifier: Operating System :: MacOS :: MacOS X
Classifier: Operating System :: Microsoft :: Windows
Requires-Dist: requests
